[
  {
    "pid": "404357135",
    "name": "삽니다 아이맥 맥북 프로 에어 맥미니 맥스튜디오 갤럭시탭 아이패드 노트북",
    "price": 7700000,
    "num_faved": 7,
    "query": "beats studio pro",
    "description": "삽니다 아이맥 맥북 프로 에어 맥미니 맥스튜디오 갤럭시탭 아이패드 노트북 / 맥북 / 태블릿 / 스마트폰 / 컴퓨터 / TV 등\n👉 전국 최고가 매입을 위해 최선을 다합니다!\n\n▶ 문의 방법 안내\n판매(매입)를 원하시는 제품의 아래 정보를\n👉 번개톡으로 보내주세요\n0. 모델명\n1. 스펙 (CPU / RAM / 용량 등)\n2. 구성품 (박스, 충전기 등)\n3. 제품 상태\n4. 상세 사진\n📩 보내주시면\n👉 빠르고 정확한 최고가 견적 안내드리겠습니다\n✔ 저희는 매입 전문 업체에요👉 판매는 하지 않습니다\n고객님의 제품을 👉 정직한 기준으로 최고가에 삽니다\n\n※ 번개톡 이용 방법\n👉 번개톡 아이콘 클릭 → ‘다른 문의가 있어요’ 선택\n✔ 보다 빠른 상담을 위해 꼭 글내용 모든 확인 후 문의 부탁드립니다!\n🌈 17년 이상 운영된 IT 기기 매입 전문 회사\n비엔엔(BNN) 입니다.\n\n📌 매입 대상 안내\n✔ 2015년 이후 출시 제품 매입 가능\n✔출시 원가가 20만원 이하인 저가형 모델은 불가요\n\n🎯 BNN의 약속\n✔고객님과의 신뢰를 가장 중요하게 생각합니다.\n✔항상 최고가 매입 견적을 위해 노력합니다\n✔빠르고 편안한 거래를 최우선으로 합니다\n✔이유 없는 가격 차감은 절대 하지 않습니다\n✔17년 업력으로 신뢰 있는 거래를 약속드립니다!\n\n🚫 장물·도난(주운것 등)품은 절대 매입하지 않습니다\n(해당 문의 시 즉시 신고 조치)\n\n🏆 17년의 역사, 검증된 신뢰\nBNN은 2008년부터 현재까지\n👉 17년 동안 꾸준히 운영된 회사입니다\n✔ 뉴스 / 언론 / 신문 보도 다수\n✔ 장기간 번개장터 활동\n✔ 실제 거래 후기 다수 보유\n\n👉 단기 업체가 아닌\n오래 검증된 안전한 매입 업체입니다\n💎 거래의 핵심 가치\n✔ 최고가 매입\n✔ 빠른 처리\n✔ 투명한 거래\n👉 고객님의 IT 기기를\n정직하게 평가하고 안전하게 거래합니다\n💬 고객 만족 최우선\n✔ 실제 거래 후기 다수\n✔ 재거래 고객 지속 증가\n👉 상담부터 거래 완료까지\n신속 · 정확 · 믿을 수 있는 서비스 제공\n💰 매입 가능 금액\n💻 노트북 / 맥북 / 태블릿 / 스마트폰 등\n👉 10만원 ~ 최대 1,000만원까지 매입 가능\n※ 제품 상태 및 사양에 따라 변동됩니다\n🚚 거래 방식 안내\n✔ 서울 / 인천 / 경기 / 전국 가능\n👉 카카오T 퀵 기사\n→ 약 15분 내 방문 가능\n\n📍 업체 위치\n인천 청라\n7호선 석남역 / 청라\n\n✔ 거래 방식\n직접 ",
    "condition": "LIGHTLY_USED",
    "sale_status": "SELLING",
    "is_proshop": false,
    "sales_count": 127,
    "review_rating": 5,
    "review_count": 111,
    "parse_ready": false,
    "reject_reasons": [
      "price_too_high",
      "missing_비츠_beats",
      "missing_any_스튜디오_s_프로_스튜디오프로_studio_",
      "reject_buying_post"
    ]
  },
  {
    "pid": "404383965",
    "name": "삽니다 / 맥북 프로 에어 맥미니 아이맥 맥스튜디오 아이패드 갤럭시탭",
    "price": 5000000,
    "num_faved": 9,
    "query": "beats studio pro",
    "description": "⭐️꼭! 제 닉네임 클릭해서 번개장터 제상점 공지사항 글 내용을  읽어주세요!!\n\n메인 계정이 따로 있으니 거기로 번개톡해주세요! (제상점 닉네임 클릭후, 공지사항 천천히 읽어봐주셔요!  이글은 광고용 입니다!! )\n\n저희가 삽니다. 저희가 구매만 합니다. 판매는 안해요.\n.\n비엔엔 매입 업체  드림\n.\n\n⭐️반드시!! 제 상점 닉네임 클릭 (제상점 메인화면)후 맨위에 있는 공지사항을 읽어보시고 문의주세요!!!\n.\n.\n-------------------------\n⭐️안녕하세요!  사업한지, 15년 넘은 매입 전문 회사 입니다!  뉴스 / Tv에도 여러번 나왔습니다!\n본문에 첨부된 사진들/ 거래후기들을 보시면 신뢰 확인 되실겁니다.\n저희가 구입(매입)만 하고 판매는 하지 않습니다!\n-------------------------\n⭐️판매(매입) 원하시는 제품의 \n모델명/구성/스펙/상태/사진  을 번개톡 남겨주시면\n좋은 견적 드리겠습니다!\n-------------------------\n⭐️2015년 이후 제품 매입중입니다!\n너무 오래됬거나 저가형은 매입 안합니다ㅠ\n⭐️약속 드립니다\n0. 매입 최고가의 견적을 낼수 있도록 항상 노력하겠습니다.\n1.  빠르고 편안한 거래가 되도록 노력하겠습니다.\n2. 이유없는 차감을 하지 않습니다\n3. 15년 넘은 회사 답게 신뢰가 최우선인 매입 회사 입니다.\n4. 장물(주운것)/도난 물건 안삽니다. 문의시 경찰서 신고!\n☆\n서울/경기/지방 15분 내외 담당 퀵기사님 방문가능!\n저희업체는 인천 청라(서울 인근) 지역에 위치하고 있어요.\n인천 청라 인근으로 오셔도 되고 택배/퀵으로 보내주셔도 됩니다!:) 퀵 진행시 당일 처리 됩니다.^^ 번개장터에서 빠르게! 진행됩니다\n\n감사합니다. 본문에 첨부된 사진들 넘겨서 꼭 다 봐보세요!\n\n노트북매입 가격은10만원~1000만원 \n컴퓨터매입 가격은 10-2000만원\n맥북매입 가격은10만원~1000만원\n태블릿매입 가격은10만원~1000만원\n기타 전자기기 가격은10만원~1000만원\n\n\n⭐️감사합니다. 본문에 첨부된 사진들 넘겨서 꼭 다 봐보세요! 상점 닉네임 클릭후,  거래후기 들도 많이 봐주셔요~~!",
    "condition": "LIGHTLY_USED",
    "sale_status": "SELLING",
    "is_proshop": false,
    "sales_count": 178,
    "review_rating": 4.9,
    "review_count": 138,
    "parse_ready": false,
    "reject_reasons": [
      "price_too_high",
      "missing_비츠_beats",
      "missing_any_스튜디오_s_프로_스튜디오프로_studio_",
      "reject_buying_post"
    ]
  },
  {
    "pid": "405838333",
    "name": "애플 닥터드레 Beats Studio Pro 브라운 풀박스",
    "price": 199000,
    "num_faved": 1,
    "query": "beats studio pro",
    "description": "제조년월 2025년2월 제조입니다.\n상태 매우 좋으며 2회정도 사용후 다른제품선물받아 \n가지고만 있어 판매합니다.\n\n내부 구성품 모두 새것이며 \n사용감이 없을 정도로 깔끔합니다.\n\n-애플 비츠 스튜디오 프로는 애플 상품 뿐만 아니라 \n안드로이드 기기와도 원활한 호환이 가능합니다.\n\n-충전이 빠르고 출퇴근시 사용하면 한참 사용가능 합니다.\n\n착용감 - 장시간 착용해도 귀 안 아픈 제품으로 유명합니다.\n\n전체적으로 디자인, 착용감, 음악 감상용 노이즈 캔슬링, 휴대성까지 균형 잡힌 제품이라 귀 통증 때문에 이어폰 사용이 힘드신 분들께 추천드립니다.",
    "condition": "LIKE_NEW",
    "sale_status": "SELLING",
    "is_proshop": false,
    "sales_count": 6,
    "review_rating": 5,
    "review_count": 2,
    "parse_ready": true,
    "reject_reasons": []
  },
  {
    "pid": "404746456",
    "name": "Beats Studio Pro 무선 헤드폰 네이비",
    "price": 200000,
    "num_faved": 0,
    "query": "beats studio pro",
    "description": "1년 전 구매했고 얼마 안 썻어요 상태 아주 좋습니다 소리 잘 들려요",
    "condition": "LIGHTLY_USED",
    "sale_status": "SELLING",
    "is_proshop": false,
    "sales_count": 0,
    "review_rating": 0,
    "review_count": 0,
    "parse_ready": true,
    "reject_reasons": []
  },
  {
    "pid": "393579993",
    "name": "Beats Studio Pro 블랙 무선 헤드폰 미개봉",
    "price": 210000,
    "num_faved": 5,
    "query": "beats studio pro",
    "description": "비츠 스튜디오 프로 블랙 무선 헤드폰입니다. 깔끔한 블랙 색상이라 어느 룩에나 잘 어울립니다. 무선이라 편하게 사용 가능하고, 노이즈 캔슬링 기능도 탑재되어 있습니다. 문의 없으시면 바로 안전결제해주시면 됩니다!\n\n새상품 급처!\n수원 금곡동 봉담2지구 상리 직거래 가능!!",
    "condition": "NEW",
    "sale_status": "SELLING",
    "is_proshop": false,
    "sales_count": 0,
    "review_rating": 0,
    "review_count": 0,
    "parse_ready": true,
    "reject_reasons": []
  },
  {
    "pid": "371542180",
    "name": "장원영헤드폰 애플 Beats Studio Pro 샌드스톤 헤드폰 새상품",
    "price": 280000,
    "num_faved": 5,
    "query": "beats studio pro",
    "description": "미개봉 애플 Beats Studio Pro 샌드스톤 색상 헤드폰입니다. 톤 다운된 베이지 색상\n\n새상품이에요 채팅주시면 사진 다드려요 직거래도가눙합니다",
    "condition": "NEW",
    "sale_status": "SELLING",
    "is_proshop": false,
    "sales_count": 3,
    "review_rating": 0,
    "review_count": 0,
    "parse_ready": true,
    "reject_reasons": []
  },
  {
    "pid": "368626390",
    "name": "애플 Beats Studio Pro 블랙 헤드폰",
    "price": 200000,
    "num_faved": 12,
    "query": "beats studio pro",
    "description": "Beats Studio Pro 무선 헤드폰 블랙 색상입니다\n\n- 액티브 노이즈 캔슬링 기능\n- 공간 음향 지원\n- 최대 40시간 배터리\n- 접이식 디자인\n\n박스는 없어요\n2번 밖에 착용 안 해서 기스 없어요\n상태 최상입니다\n정가에 비해 매우 합리적인 가격인 듯 합니다",
    "condition": "LIKE_NEW",
    "sale_status": "SELLING",
    "is_proshop": false,
    "sales_count": 5,
    "review_rating": 5,
    "review_count": 3,
    "parse_ready": true,
    "reject_reasons": []
  },
  {
    "pid": "404560462",
    "name": "애플 Beats Studio Pro 블랙 헤드폰 애플 비츠 스튜디오 프로",
    "price": 150000,
    "num_faved": 2,
    "query": "beats studio pro",
    "description": "구매한지 2년정도됐습니다\n실사용 10회 이하",
    "condition": "LIGHTLY_USED",
    "sale_status": "SOLD_OUT",
    "is_proshop": false,
    "sales_count": 161,
    "review_rating": 4.9,
    "review_count": 62,
    "parse_ready": true,
    "reject_reasons": []
  },
  {
    "pid": "398267470",
    "name": "Beats Studio Pro 비츠 스튜디오 프로 블랙",
    "price": 160000,
    "num_faved": 1,
    "query": "beats studio pro",
    "description": "사용감 거의없고 깨끗합니다\n쿨거시 택포",
    "condition": "LIKE_NEW",
    "sale_status": "SOLD_OUT",
    "is_proshop": false,
    "sales_count": 1,
    "review_rating": 0,
    "review_count": 0,
    "parse_ready": true,
    "reject_reasons": []
  },
  {
    "pid": "391182526",
    "name": "Beats Studio Pro 비츠 스튜디오 프로 세드셋",
    "price": 200000,
    "num_faved": 7,
    "query": "beats studio pro",
    "description": "비츠 스튜디오 프로 헤드셋 검정 입니다.\n\n1년 반 정도 전, 헤드셋 병에 걸려 직접 매장에서 구매하였지만, 헤드셋이 어울리지 않아 거의 사용하지 않았습니다.\n\n사용은 실외 착용 0회 , 실내 영화 감상 10회 정도 될것 같습니다.\n거의 새 제품이라고 보시면 될 것 같습니다.\n\n풀 박스이고, 사진에서 보시다시피 유선 잭은 새 제품 포장 그대로 둘 정도로 사용감이 없습니다.\n\n하자 전혀 없습니다.\n아마 계속 책상위 악세사리로 두기만 할 것 같아, 멋지게 사용해 줄 새 주인분을 찾습니다.\n\n편하게 연락주세요~",
    "condition": "LIKE_NEW",
    "sale_status": "SOLD_OUT",
    "is_proshop": false,
    "sales_count": 4,
    "review_rating": 5,
    "review_count": 3,
    "parse_ready": true,
    "reject_reasons": []
  },
  {
    "pid": "392657811",
    "name": "Apple 애플 정품 Beats Studio Pro 비츠 스튜디오 헤드셋",
    "price": 110000,
    "num_faved": 2,
    "query": "beats studio pro",
    "description": "애플 정품 Beats Studio Pro 무선 헤드폰입니다. 색상이 고급스럽고 예뻐요. 블루투스연결잘되고 무선이라 편리하고, 음질도 정말 좋습니다. 별도 문의 없으시면 바로 안전결제 해주시면 됩니다!\n실사용 한번 후 보관중입이며 충전기와 정품케이스도\n함께 드립니다",
    "condition": "LIKE_NEW",
    "sale_status": "SOLD_OUT",
    "is_proshop": false,
    "sales_count": 31,
    "review_rating": 5,
    "review_count": 28,
    "parse_ready": false,
    "reject_reasons": [
      "price_too_low"
    ]
  },
  {
    "pid": "393266157",
    "name": "미개봉 Beats Studio Pro 무선 헤드폰 블랙",
    "price": 250000,
    "num_faved": 3,
    "query": "beats studio pro",
    "description": "Apple 정품 Beats Studio Pro 무선 헤드폰 블랙 색상 미개봉 제품입니다\n- 미사용 새 제품입니다 (미국구매)\n- 하단면애 박스 찌그러짐 있으나, 아예 뜯지 않은 미개봉 새상품이고 안전 실 확인하실 수 있습니다 (사진참고)",
    "condition": "NEW",
    "sale_status": "SOLD_OUT",
    "is_proshop": false,
    "sales_count": 11,
    "review_rating": 5,
    "review_count": 3,
    "parse_ready": true,
    "reject_reasons": []
  },
  {
    "pid": "385508554",
    "name": "Apple 정품 Beats Studio Pro 무선 헤드폰",
    "price": 150000,
    "num_faved": 5,
    "query": "beats studio pro",
    "description": "애플 정품 Beats Studio Pro 무선 헤드폰입니다. 무난한 색상이라 어디든 잘 어울립니다. 접이식이라 보관도 용이합니다. 별도 문의 없으시면 바로 안전결제 부탁드려요!",
    "condition": "LIKE_NEW",
    "sale_status": "SOLD_OUT",
    "is_proshop": false,
    "sales_count": 55,
    "review_rating": 4.8,
    "review_count": 49,
    "parse_ready": true,
    "reject_reasons": []
  },
  {
    "pid": "406346772",
    "name": "비츠 스튜디오 프로 헤드셋",
    "price": 120000,
    "num_faved": 3,
    "query": "beats studio pro",
    "description": "작년 4월에 구매하여 몇 번 착용한 후 계속 보관함에 넣어 두고 보관만 했습니다. 전체적으로 깨끗한 상태이며, 찍힘이나 스크래치는 전혀 없습니다. 정품 충전 케이블과 사용하지 않은 3.5mm 오디오 케이블도 함께 드립니다.",
    "condition": "LIGHTLY_USED",
    "sale_status": "SOLD_OUT",
    "is_proshop": false,
    "sales_count": 16,
    "review_rating": 5,
    "review_count": 10,
    "parse_ready": false,
    "reject_reasons": [
      "price_too_low"
    ]
  },
  {
    "pid": "396142197",
    "name": "Apple Beats Studio3 비츠 스튜디오3 ANC 헤드폰",
    "price": 45000,
    "num_faved": 2,
    "query": "beats studio pro",
    "description": "노이즈캔슬링 노캔 헤드셋 애플 비츠 스튜디오 와이어리스 제품입니다. 비츠 정품 파우치와 함께 드립니다 !\n\n모든 기능 정상작동하고 외관 상태도 아주 좋습니다:) 애플에서 나온 제품이라 에어팟처럼 애플기기랑 연동성이 좋아서 편하게 사용할수 있어요! \n\n노캔은 에어팟 프로와 맥스 사이, 음질은 에어팟 프로, 맥스보다도 좋게 느껴졌어요! 이어캡도 폭신폭신 해서 오래 끼고있어도 안아파서 좋았습니다 ㅎㅎ 기기 자체 문제는 없지만 박스가 없어서 저렴하게 판매해요!\n\n결제 전 문의 부탁드려요 !",
    "condition": "LIKE_NEW",
    "sale_status": "SOLD_OUT",
    "is_proshop": false,
    "sales_count": 382,
    "review_rating": 4.9,
    "review_count": 142,
    "parse_ready": false,
    "reject_reasons": [
      "price_too_low",
      "missing_any_스튜디오_s_프로_스튜디오프로_studio_",
      "reject_wrong_model_studio3"
    ]
  },
  {
    "pid": "407253749",
    "name": "비츠 스튜디오 프로",
    "price": 180000,
    "num_faved": 1,
    "query": "비츠 스튜디오 프로",
    "description": "비츠 스튜디오 프로 블랙색상 헤드셋 입니다 \n구매 이후 15번 이내로 착용했습니다\n손이 잘 가지 않아서 판매해요 \n노이즈 캔슬링 , 버튼 작동 이상 없습니다\n박스 없고 c타입 선 없습니다",
    "condition": "LIKE_NEW",
    "sale_status": "SELLING",
    "is_proshop": false,
    "sales_count": 16,
    "review_rating": 5,
    "review_count": 5,
    "parse_ready": true,
    "reject_reasons": []
  },
  {
    "pid": "406376164",
    "name": "비츠 스튜디오 프로 헤드셋",
    "price": 180000,
    "num_faved": 2,
    "query": "비츠 스튜디오 프로",
    "description": "비츠 스튜디오 프로 헤드셋 블랙 색상입니다\n무게는 가벼운 편이구요 착용감 정말 좋다고 생각합니다\n풀박스에 파우치까지 있어서 보관이랑 휴대하기 좋습니다\n자세한 부분 사진 문의 또는 다른 문의 있으시면 연락주시면 답해드리겠습니다 연락주세용",
    "condition": "LIKE_NEW",
    "sale_status": "SELLING",
    "is_proshop": false,
    "sales_count": 5,
    "review_rating": 5,
    "review_count": 6,
    "parse_ready": true,
    "reject_reasons": []
  },
  {
    "pid": "405222420",
    "name": "비츠 스튜디오 프로 네이비",
    "price": 165000,
    "num_faved": 6,
    "query": "비츠 스튜디오 프로",
    "description": "구매한지 3주됐어요\n실착 2회 새상품급\n\n제 머리엔 불편해서 팔아요. 헤드셋백 다 있습니다",
    "condition": "LIKE_NEW",
    "sale_status": "SELLING",
    "is_proshop": false,
    "sales_count": 8,
    "review_rating": 5,
    "review_count": 4,
    "parse_ready": true,
    "reject_reasons": []
  },
  {
    "pid": "405145178",
    "name": "비츠 스튜디오 프로 네이비",
    "price": 203000,
    "num_faved": 0,
    "query": "비츠 스튜디오 프로",
    "description": "비츠 스튜디오 프로 네이비 색상입니다. \n풀박스입니다(실착1회)",
    "condition": "LIKE_NEW",
    "sale_status": "SELLING",
    "is_proshop": false,
    "sales_count": 0,
    "review_rating": 0,
    "review_count": 0,
    "parse_ready": true,
    "reject_reasons": []
  },
  {
    "pid": "405087591",
    "name": "비츠 스튜디오 프로 네이비 (미사용)",
    "price": 180000,
    "num_faved": 11,
    "query": "비츠 스튜디오 프로",
    "description": "4월 30일 어제 배송 완료된 상품입니다.\n포장지만 뜯어봤고 야외 실착 없고 그냥 보관만 해놓은 상태입니다. \n\n비츠 스튜디오 프로 네이비 색상 헤드폰이에요\n구성품으로 케이스와 충전 케이블 포함되어 있어요\n선명하고 풍부한 사운드를 경험해보세요\n음악 감상이나 영상 시청 시 몰입감을 더해줄 거예요",
    "condition": "NEW",
    "sale_status": "SELLING",
    "is_proshop": false,
    "sales_count": 6,
    "review_rating": 5,
    "review_count": 1,
    "parse_ready": true,
    "reject_reasons": []
  },
  {
    "pid": "402683254",
    "name": "애플 비츠 스튜디오 프로 블랙",
    "price": 195000,
    "num_faved": 0,
    "query": "비츠 스튜디오 프로",
    "description": "✅ [믿고 사는 상점! 2400건 이상 안전거래 완료] ✅\n🚀 [600개 특급 후기로 최상의만족도! 빠른 배송보장] 🚀\n💯 [가품/하자 시 확인후 100%즉시 환불/교체!] 💯\n🔔 [놓치지 마세요! 수시로 업데이트되는 최신 상품 확인!] 🔔\n\n애플 비츠 스튜디오 프로 헤드셋 판매\n모델명 : 사진참조\n구성 : 헤드셋 + 파우치\n색상 : 블랙\n\n◆ 외관상태 양호함\n◆ 정상작동 테스트완료\n◆ 알콜 소독청소하여 안전하게 포장발송예정\n\n▷ 스마트한 거래 안내\n◆ 평일 2시이전 주문 시 당일 출고! (내일 바로 받아보세요!)\n◆ 상점의 다양한 판매 목록도 함께 확인! \n     (합배송 및 추가 할인 문의 환영!)\n◆ 직거래 : 김포 또는 서울 은평구에서 편리(시간 조율 가능)\n\n💡 지금 바로 문의! 당신의 스마트한 선택을 기다립니다!",
    "condition": "LIGHTLY_USED",
    "sale_status": "SELLING",
    "is_proshop": false,
    "sales_count": 2515,
    "review_rating": 4.9,
    "review_count": 761,
    "parse_ready": false,
    "reject_reasons": [
      "reject_non_beats_clone"
    ]
  },
  {
    "pid": "400041491",
    "name": "비츠 스튜디오 프로 헤드셋",
    "price": 160000,
    "num_faved": 16,
    "query": "비츠 스튜디오 프로",
    "description": "비츠 스튜디오 프로 헤드셋 판매합니다. 네이비 색상으로, 디자인이 정말 예뻐요. 음질도 훌륭해서 음악 감상이나 영화 감상할 때 몰입감을 더해줍니다.\n\n가격 : 16\n\n직/택 (+4000)",
    "condition": "NEW",
    "sale_status": "SELLING",
    "is_proshop": false,
    "sales_count": 201,
    "review_rating": 4.9,
    "review_count": 48,
    "parse_ready": true,
    "reject_reasons": []
  },
  {
    "pid": "398786702",
    "name": "애플 비츠 스튜디오 프로 블랙",
    "price": 312000,
    "num_faved": 3,
    "query": "비츠 스튜디오 프로",
    "description": "집에서만 한두번 썼어요\n상태 최상입니다",
    "condition": "LIKE_NEW",
    "sale_status": "SELLING",
    "is_proshop": false,
    "sales_count": 343,
    "review_rating": 5,
    "review_count": 112,
    "parse_ready": true,
    "reject_reasons": []
  },
  {
    "pid": "397824159",
    "name": "비츠 스튜디오 프로 블랙",
    "price": 170000,
    "num_faved": 2,
    "query": "비츠 스튜디오 프로",
    "description": "비츠 스튜디오 프로 헤드폰 블랙 색상입니다\n\n구성품은 파우치, 케이블, 풀박 구성입니다.\n상태는 매우 좋습니다.\n국내 애플스토어 구매 정품이며 구입한지는 6개월 정도 됐습니다.\n\n배송비 포함 170000원 입니다.",
    "condition": "LIGHTLY_USED",
    "sale_status": "RESERVED",
    "is_proshop": false,
    "sales_count": 0,
    "review_rating": 4.9,
    "review_count": 8,
    "parse_ready": true,
    "reject_reasons": []
  },
  {
    "pid": "399315475",
    "name": "비츠 스튜디오 프로 헤드셋 미사용입니다",
    "price": 299000,
    "num_faved": 6,
    "query": "비츠 스튜디오 프로",
    "description": "애플 정품) 비츠 스튜디오 프로 헤드셋입니다.\n 구입가 449,000원이며\n아래는 제품 정보 사이트입니다.\nhttps://naver.me/5lfDjp23\n개봉 후 보관하고있어서 저렴하게 내어놓으니 필요하신 분 연락주세요.\n\n직거래 낮에는 서울 중구 충무로 29 국민은행 앞,\n저녁은 8시 이후에 서울 서대문구 거북골로18나길 43 앞입니다.\n싼 만큼 더 이상의 내고 없으니 꼭 필요한 분만 연락주세요.",
    "condition": "NEW",
    "sale_status": "SELLING",
    "is_proshop": false,
    "sales_count": 231,
    "review_rating": 4.9,
    "review_count": 58,
    "parse_ready": true,
    "reject_reasons": []
  },
  {
    "pid": "397857994",
    "name": "비츠 스튜디오 프로 무선 헤드폰 네이비 새상품",
    "price": 180000,
    "num_faved": 0,
    "query": "비츠 스튜디오 프로",
    "description": "비츠 스튜디오 프로 무선 헤드폰 네이비 새상품입니다\n\n개봉안한 박스채로 들고있습니다\n\n교환환불 불가합니다",
    "condition": "NEW",
    "sale_status": "RESERVED",
    "is_proshop": false,
    "sales_count": 16,
    "review_rating": 5,
    "review_count": 5,
    "parse_ready": true,
    "reject_reasons": []
  },
  {
    "pid": "395090047",
    "name": "비츠 스튜디오 프로 블랙",
    "price": 170000,
    "num_faved": 12,
    "query": "비츠 스튜디오 프로",
    "description": "실내에서 음악 감상용으로 깨끗하게 사용했습니다\n윗부분 약간의 생활 기스 존재합니다\n\n구성품: 사진에 보이는 것 전부\n(aux 단자, 파우치 , 헤드셋)",
    "condition": "LIGHTLY_USED",
    "sale_status": "RESERVED",
    "is_proshop": false,
    "sales_count": 35,
    "review_rating": 4.6,
    "review_count": 10,
    "parse_ready": true,
    "reject_reasons": []
  },
  {
    "pid": "392627060",
    "name": "스투시 비츠스튜디오프로 헤드셋 콜라보 미개봉 헤드셋",
    "price": 940000,
    "num_faved": 5,
    "query": "비츠 스튜디오 프로",
    "description": "당시 한정판으로 나온제품이었고 \n구매후 상자 그대로 뜯지도 않고 그대로 \n미개봉상태 보관중입니다 .\n타 사이트 250~후반대입니다\n그 이외는 정품 아닌걸로 알고있어요\n*직거래 강남 수원 가능입니다.\n구매자분들 중 서울 사시는 분들 있으시면 알려주세요",
    "condition": "NEW",
    "sale_status": "SELLING",
    "is_proshop": false,
    "sales_count": 2,
    "review_rating": 5,
    "review_count": 1,
    "parse_ready": false,
    "reject_reasons": [
      "price_too_high"
    ]
  },
  {
    "pid": "372010448",
    "name": "비츠 스튜디오 프로 신품 20에 던짐 제발",
    "price": 200000,
    "num_faved": 9,
    "query": "비츠 스튜디오 프로",
    "description": "교신은 카본 88림만\n미개봉 신품입니다\n돈이급해서 가격 내립니다\n선물받았는데 안써서 팔아요\n직거래 선호해요\n색은 갈색입니다\n택포 21",
    "condition": "NEW",
    "sale_status": "RESERVED",
    "is_proshop": false,
    "sales_count": 0,
    "review_rating": 0,
    "review_count": 0,
    "parse_ready": true,
    "reject_reasons": []
  },
  {
    "pid": "342182419",
    "name": "비츠 스튜디오 프로 브라운",
    "price": 83000,
    "num_faved": 3,
    "query": "비츠 스튜디오 프로",
    "description": "Beats Studio Pro 샌드스톤 브라운 색상 헤드폰입니다\n상태는 사진과 같습니다\n떨어트려서 헤어밴드 쪽에 스크래치가 있습니다\n\n\n- Apple H2 칩 탑재\n- 액티브 노이즈 캔슬링 기능\n- 공간 오디오 지원\n- 최대 40시간 청취 가능\n- USB-C 충전 케이블, 휴대용 케이스 포함\n\n정가는 479,000원이에요\n박스도 같이 드립니다",
    "condition": "HEAVILY_USED",
    "sale_status": "RESERVED",
    "is_proshop": false,
    "sales_count": 3,
    "review_rating": 0,
    "review_count": 0,
    "parse_ready": false,
    "reject_reasons": [
      "price_too_low"
    ]
  },
  {
    "pid": "338849342",
    "name": "비츠 스튜디오 프로 헤드셋 갈색",
    "price": 200000,
    "num_faved": 15,
    "query": "비츠 스튜디오 프로",
    "description": "사용감 좀 있어요! 머리부분 좀 까져있는 정도?\n(티는 별로 안나요.!!)\n27만원대에 구매했었습니당\n가격제안 환영 !! (급처라ㅠㅠ)\n편하게 연락주세용\n\n*쿨거시 18만까지는 네고 의향 있음",
    "condition": "LIGHTLY_USED",
    "sale_status": "SELLING",
    "is_proshop": false,
    "sales_count": 0,
    "review_rating": 0,
    "review_count": 0,
    "parse_ready": true,
    "reject_reasons": []
  },
  {
    "pid": "334750861",
    "name": "비츠 스튜디오 프로3",
    "price": 90000,
    "num_faved": 53,
    "query": "비츠 스튜디오 프로",
    "description": "박스가 없어서 감안한 가격에 판매합니다\n새것처럼 잘 작동하고 깔끔,깨끗 합니다 ~",
    "condition": "LIKE_NEW",
    "sale_status": "SELLING",
    "is_proshop": false,
    "sales_count": 2,
    "review_rating": 5,
    "review_count": 1,
    "parse_ready": false,
    "reject_reasons": [
      "price_too_low"
    ]
  },
  {
    "pid": "407214422",
    "name": "(가격제안 환영) 비츠 스튜디오 프로 새상품",
    "price": 190000,
    "num_faved": 0,
    "query": "비츠 스튜디오 프로",
    "description": "교환, 환불 안됩니다 !!꼭 !!설명 꼭!!상세 사이즈\n확인해 주세요!!\n\n개봉만 하고 사용 1번도 안한  비트 스튜디오 프로입니다. \n구매 시 같이 사용하려고 했던 케이스도 함께 드려요!\n\n고급스러운 베이지 색상이며, 새상품인 만큼 문의 없으시면 바로 안전결제해주시면 됩니다!",
    "condition": "NEW",
    "sale_status": "SOLD_OUT",
    "is_proshop": false,
    "sales_count": 6,
    "review_rating": 5,
    "review_count": 8,
    "parse_ready": true,
    "reject_reasons": []
  },
  {
    "pid": "406996510",
    "name": "비츠 스튜디오 프로 블랙",
    "price": 170000,
    "num_faved": 2,
    "query": "비츠 스튜디오 프로",
    "description": "제한 보증 남아있고, C타입 없이 풀박스 구성(3.5mm잭, 케이스, 설명서, 박스, 박스커버)입니다.\n\n작동 잘 되고 에어팟 쓰다가 새걸로 샀는데 저한테는 이어폰이 맞는 것 같아 판매합니다.",
    "condition": "LIKE_NEW",
    "sale_status": "SOLD_OUT",
    "is_proshop": false,
    "sales_count": 9,
    "review_rating": 5,
    "review_count": 3,
    "parse_ready": true,
    "reject_reasons": []
  },
  {
    "pid": "405632865",
    "name": "비츠 스튜디오 프로 블랙 (미개봉)국내정발",
    "price": 225000,
    "num_faved": 0,
    "query": "비츠 스튜디오 프로",
    "description": "친구 선물로 구매했는데 이미 헤드셋이 있다고해서 재판매 합니다 ㅠㅠ 미개봉 새상품이고 쿠팡 구매 제품이에요! 인증가능합니다",
    "condition": "NEW",
    "sale_status": "SOLD_OUT",
    "is_proshop": false,
    "sales_count": 38,
    "review_rating": 5,
    "review_count": 34,
    "parse_ready": true,
    "reject_reasons": []
  },
  {
    "pid": "402561046",
    "name": "비츠 스튜디오 프로",
    "price": 200000,
    "num_faved": 5,
    "query": "비츠 스튜디오 프로",
    "description": "새상품급 비츠 스튜디오 프로 팝니당\n\n박스만 없는 새상품급 입니다.\n\n충전기,파우치 모두 드립니다!!",
    "condition": "LIKE_NEW",
    "sale_status": "SOLD_OUT",
    "is_proshop": false,
    "sales_count": 7,
    "review_rating": 5,
    "review_count": 8,
    "parse_ready": true,
    "reject_reasons": []
  },
  {
    "pid": "403358361",
    "name": "비츠 스튜디오 프로 브라운 색상",
    "price": 180000,
    "num_faved": 0,
    "query": "비츠 스튜디오 프로",
    "description": "비츠 스튜디오 프로 브라운 컬러입니다.\n상태 좋고 풀박스입니다.\n직거래는 6호선 월곡역 부근이며 택배거래시 배송비 별도입니다.",
    "condition": "LIKE_NEW",
    "sale_status": "SOLD_OUT",
    "is_proshop": false,
    "sales_count": 20,
    "review_rating": 5,
    "review_count": 15,
    "parse_ready": true,
    "reject_reasons": []
  },
  {
    "pid": "403570215",
    "name": "비츠 스튜디오 프로 무선 오버 이어 헤드폰 블랙",
    "price": 120000,
    "num_faved": 3,
    "query": "비츠 스튜디오 프로",
    "description": "집에서만 노래 듣는 다고 몇번 사용한 게 끝인 제품입니다.",
    "condition": "LIKE_NEW",
    "sale_status": "SOLD_OUT",
    "is_proshop": false,
    "sales_count": 26,
    "review_rating": 5,
    "review_count": 4,
    "parse_ready": false,
    "reject_reasons": [
      "price_too_low"
    ]
  },
  {
    "pid": "402088843",
    "name": "애플 비츠 스튜디오 프로 블랙",
    "price": 180000,
    "num_faved": 2,
    "query": "비츠 스튜디오 프로",
    "description": "애플 비츠 스튜디오 프로 블랙 색상입니다. 전체적으로 깔끔한 외관을 유지하고 있습니다. 음질도 아주 좋으니 편하게 사용하실 분들께 추천드려요. 별도 문의 없으시면 바로 안전결제 부탁드려요!  헤드폰 스펀지 갈라짐없고 엄청 깨끗합니다. 전용 충전선있고 쿠팡에서 구입했습니다. 그리고 실착 집에서만 몇번끼고 밖에서 낀적 한번도 없습니다",
    "condition": "LIKE_NEW",
    "sale_status": "SOLD_OUT",
    "is_proshop": false,
    "sales_count": 42,
    "review_rating": 5,
    "review_count": 16,
    "parse_ready": true,
    "reject_reasons": []
  },
  {
    "pid": "400984421",
    "name": "비츠스튜디오프로",
    "price": 120000,
    "num_faved": 2,
    "query": "비츠 스튜디오 프로",
    "description": "비츠 스튜디오 프로 블랙 색상입니다. 전체적으로 깔끔하게 사용해서 상태 좋습니다. 음질도 괜찮고, 디자인도 예뻐서 만족하실 거에요. 문의 없으시면 바로 안전결제해주시면 됩니다!\n보증기간 10월까지 남아있습니다.",
    "condition": "LIGHTLY_USED",
    "sale_status": "SOLD_OUT",
    "is_proshop": false,
    "sales_count": 13,
    "review_rating": 5,
    "review_count": 3,
    "parse_ready": false,
    "reject_reasons": [
      "price_too_low"
    ]
  },
  {
    "pid": "401275844",
    "name": "애플 비츠 스튜디오 프로",
    "price": 139000,
    "num_faved": 1,
    "query": "비츠 스튜디오 프로",
    "description": "구매 후 헤드폰 보다는 이어폰 사용이 많아 사용감이 적지만 생활 찍힘 및 기스 조금 있습니다. 구성품은 파우치를 분실하여 사진에 나온 그대로 입니다. 저렴하게 판매해 봅니다. 네고 및 결제 문의 외 답장은 가지 않습니다.",
    "condition": "LIGHTLY_USED",
    "sale_status": "SOLD_OUT",
    "is_proshop": false,
    "sales_count": 18,
    "review_rating": 4.7,
    "review_count": 19,
    "parse_ready": false,
    "reject_reasons": [
      "price_too_low"
    ]
  },
  {
    "pid": "400383742",
    "name": "애플 비츠 스튜디오 프로",
    "price": 150000,
    "num_faved": 2,
    "query": "비츠 스튜디오 프로",
    "description": "비츠 스튜디오 프로 샌드스톤 색상 이쁩니다!!\n실사용 얼마 안해서 상태는 진짜 좋습니다\n방탄 정국 제니 외 다른 유명인들이 극찬한 제품입니다",
    "condition": "LIKE_NEW",
    "sale_status": "SOLD_OUT",
    "is_proshop": false,
    "sales_count": 19,
    "review_rating": 5,
    "review_count": 10,
    "parse_ready": true,
    "reject_reasons": []
  },
  {
    "pid": "400477636",
    "name": "비츠 스튜디오 프로 딥브라운",
    "price": 184000,
    "num_faved": 0,
    "query": "비츠 스튜디오 프로",
    "description": "비츠 스튜디오 프로 딥브라운 색상입니다. 사진에서 보시는 것처럼 이어컵이 푹신해서 착용감이 좋습니다.\n\n미 개봉 새 상품\n\n가격 : 18.4\n\n직/택(+4000)",
    "condition": "NEW",
    "sale_status": "SOLD_OUT",
    "is_proshop": false,
    "sales_count": 201,
    "review_rating": 4.9,
    "review_count": 48,
    "parse_ready": true,
    "reject_reasons": []
  },
  {
    "pid": "400041983",
    "name": "비츠 스튜디오 프로 딥브라운",
    "price": 184000,
    "num_faved": 3,
    "query": "비츠 스튜디오 프로",
    "description": "비츠 스튜디오 프로 딥브라운 색상입니다. 고급스러운 딥브라운 색상이 아주 매력적입니다. 음질도 훌륭하고, 디자인도 예뻐서 만족하실 거에요.\n\n가격 : 18\n\n직/택(+4000)\n\n미개봉 새 상품",
    "condition": "NEW",
    "sale_status": "SOLD_OUT",
    "is_proshop": false,
    "sales_count": 201,
    "review_rating": 4.9,
    "review_count": 48,
    "parse_ready": true,
    "reject_reasons": []
  },
  {
    "pid": "399653989",
    "name": "애플 비츠 스튜디오 프로 블랙",
    "price": 210000,
    "num_faved": 1,
    "query": "비츠 스튜디오 프로",
    "description": "개봉만한 새상품입니다. \n\n색상 : 블랙\n\n기기 정상작동 확인 차 개봉하였으며 보증도 1년 살아있습니다. \n\n저렴하게 가져가세요",
    "condition": "NEW",
    "sale_status": "SOLD_OUT",
    "is_proshop": false,
    "sales_count": 36,
    "review_rating": 4.7,
    "review_count": 19,
    "parse_ready": true,
    "reject_reasons": []
  },
  {
    "pid": "398979647",
    "name": "비츠 스튜디오 프로 헤드셋",
    "price": 160000,
    "num_faved": 5,
    "query": "비츠 스튜디오 프로",
    "description": "비츠 스튜디오 프로 헤드셋 판매합니다. 무난한 네이비 색상이라 어디든 잘 어울립니다.\n\n미 개봉 새 상품\n\n가격 : 16\n\n직 / 택 ( + 4000 )",
    "condition": "NEW",
    "sale_status": "SOLD_OUT",
    "is_proshop": false,
    "sales_count": 201,
    "review_rating": 4.9,
    "review_count": 48,
    "parse_ready": true,
    "reject_reasons": []
  },
  {
    "pid": "399281300",
    "name": "비츠 스튜디오 프로 블랙 s급",
    "price": 180000,
    "num_faved": 5,
    "query": "비츠 스튜디오 프로",
    "description": "비츠 스튜디오 프로 블랙 색상 S급 제품입니다. 사진에서 보시는 것처럼 거의 새것과 동일한 컨디션 유지하고 있습니다. 음질 빵빵하고 디자인도 너무 예뻐서 만족하실 거에요. 문의 없으시면 바로 안전결제해주시면 됩니다!\n실착 10회\n11월에 구매해서 1월까지 간간히 쓰다가 보관중입니다",
    "condition": "LIKE_NEW",
    "sale_status": "SOLD_OUT",
    "is_proshop": false,
    "sales_count": 1,
    "review_rating": 0,
    "review_count": 0,
    "parse_ready": true,
    "reject_reasons": []
  },
  {
    "pid": "397309404",
    "name": "비츠 스튜디오 프로 네이비",
    "price": 160000,
    "num_faved": 5,
    "query": "비츠 스튜디오 프로",
    "description": "비츠 스튜디오 프로 네이비 색상 헤드폰입니다. \n\n미 개봉 새 상품\n\n가격 : 16\n\n당일 발송 가능\n\n쿨거시 택포 해드립니다. 감사합니다.",
    "condition": "NEW",
    "sale_status": "SOLD_OUT",
    "is_proshop": false,
    "sales_count": 201,
    "review_rating": 4.9,
    "review_count": 48,
    "parse_ready": true,
    "reject_reasons": []
  },
  {
    "pid": "397363226",
    "name": "비츠 스튜디오 프로 블랙",
    "price": 175000,
    "num_faved": 4,
    "query": "비츠 스튜디오 프로",
    "description": "비츠 스튜디오 프로 블랙 색상 헤드폰입니다. 깔끔한 블랙 색상이라 어느 룩에나 잘 어울립니다. 작년에 구매했어요 눈에띄는 하자 없습니다 상세사진 보고싶으시면 챗주세요 정상작동합니다 연결 음질 문제 없습니다\n 문의 없으시면 바로 안전결제해주시면 됩니다!",
    "condition": "LIKE_NEW",
    "sale_status": "SOLD_OUT",
    "is_proshop": false,
    "sales_count": 10,
    "review_rating": 5,
    "review_count": 10,
    "parse_ready": true,
    "reject_reasons": []
  },
  {
    "pid": "395832702",
    "name": "비츠스튜디오프로 딥브라운 헤드셋 / s급",
    "price": 130000,
    "num_faved": 1,
    "query": "비츠 스튜디오 프로",
    "description": "Beats Studio Pro 케이스 포함입니다. \n색상이 진짜 예뻐요. 남녀노소 잘어울리고 핏도 예뻐요!\n\n외관 기스는 없지만 보시다시피 쿠션에 약간의 이염이 있 습니다.\n자주 사용하지 않아 상태는 아주 좋고 배터리나 작동 이상 없습니다.",
    "condition": "LIKE_NEW",
    "sale_status": "SOLD_OUT",
    "is_proshop": false,
    "sales_count": 1,
    "review_rating": 0,
    "review_count": 0,
    "parse_ready": false,
    "reject_reasons": [
      "price_too_low"
    ]
  },
  {
    "pid": "394694017",
    "name": "비츠 스튜디오 프로 블랙",
    "price": 190000,
    "num_faved": 12,
    "query": "비츠 스튜디오 프로",
    "description": "구매 후 잘 사용하지 않아 판매합니다.\n\n상태 : 판매완료\n특징 : 구성품 모두 보유중 (케이블, 충전기, 박스)\n\n애플 제품이라 아이폰이랑 연동성도 좋고 나의 찾기도 지원합니다. 무엇보다 시중에 나온 블루투스 헤드셋 중 가장 예뻐요",
    "condition": "LIKE_NEW",
    "sale_status": "SOLD_OUT",
    "is_proshop": false,
    "sales_count": 4,
    "review_rating": 5,
    "review_count": 1,
    "parse_ready": true,
    "reject_reasons": []
  },
  {
    "pid": "394277841",
    "name": "비츠 스튜디오 프로",
    "price": 160000,
    "num_faved": 1,
    "query": "비츠 스튜디오 프로",
    "description": "비츠 스튜디오 프로 블랙 색상입니다. 보증 26.6.26일 까지 남아있고 구성품은 케이스랑 헤드폰 단품입니다.",
    "condition": "LIGHTLY_USED",
    "sale_status": "SOLD_OUT",
    "is_proshop": false,
    "sales_count": 119,
    "review_rating": 4.7,
    "review_count": 30,
    "parse_ready": true,
    "reject_reasons": []
  },
  {
    "pid": "394793387",
    "name": "비츠 스튜디오 프로 + 애플케어",
    "price": 140000,
    "num_faved": 3,
    "query": "비츠 스튜디오 프로",
    "description": "비츠 스튜디오 프로 블랙색상 판매합니나.\n구성품은 본품과 파우치이며, 애플케어 적용되어 있어서 26년 6월 15일 전까지 사용하시다가 교환 받으시면 될 것 같습니다.\n\n출퇴근시 주로 사용했으며, 노이즈 캔슬링 기능 있습니다.\n\n직거래는 천호역 1번 출구쪽에서 가능하며 택배 거래시 +3,000원(쿨거래시 택배비 네고 가능) 입니다",
    "condition": "LIGHTLY_USED",
    "sale_status": "SOLD_OUT",
    "is_proshop": false,
    "sales_count": 18,
    "review_rating": 5,
    "review_count": 5,
    "parse_ready": false,
    "reject_reasons": [
      "price_too_low"
    ]
  },
  {
    "pid": "395486590",
    "name": "비츠 스튜디오 프로 무선 오버 이어 헤드폰 블랙",
    "price": 160000,
    "num_faved": 5,
    "query": "비츠 스튜디오 프로",
    "description": "원가 30만원 주고 샀고 5회 미만 착용했습니다.\n기스 하나도 없고 연결 잭, 파우치, 충전기 구성품 다 있습니다.  쓸 일이 없어서 팔아요!",
    "condition": "LIKE_NEW",
    "sale_status": "SOLD_OUT",
    "is_proshop": false,
    "sales_count": 1,
    "review_rating": 5,
    "review_count": 1,
    "parse_ready": true,
    "reject_reasons": []
  },
  {
    "pid": "392257714",
    "name": "애플 비츠 스튜디오 프로3",
    "price": 180000,
    "num_faved": 2,
    "query": "비츠 스튜디오 프로",
    "description": "애플 비츠 스튜디오 프로3 매트블랙\n노이즈캔슬링 가능\n\n스티커 떼다가 왼쪽에 스크래치 생겼습니다ㅠㅠ\n사용량 적고, 소장하다 판매합니다",
    "condition": "LIGHTLY_USED",
    "sale_status": "SOLD_OUT",
    "is_proshop": false,
    "sales_count": 52,
    "review_rating": 5,
    "review_count": 14,
    "parse_ready": true,
    "reject_reasons": []
  },
  {
    "pid": "391207130",
    "name": "비츠 스튜디오 프로 블랙",
    "price": 180000,
    "num_faved": 6,
    "query": "비츠 스튜디오 프로",
    "description": "블랙 색생이구요 구성품은 파우치랑 충전선 새거, 본체 입니다 본체도 거이 사용하지 않아서 깨끗합니다! \n파우치만 겉에 까진거 외에는 이상 없습니다 !",
    "condition": "LIKE_NEW",
    "sale_status": "SOLD_OUT",
    "is_proshop": false,
    "sales_count": 10,
    "review_rating": 4.7,
    "review_count": 6,
    "parse_ready": false,
    "reject_reasons": [
      "reject_case_or_pouch_only"
    ]
  },
  {
    "pid": "391355325",
    "name": "비츠 스튜디오 프로 블랙 판매합니다",
    "price": 150000,
    "num_faved": 0,
    "query": "비츠 스튜디오 프로",
    "description": "25년8월 구매했고 외출 한 3-4번? \n집에서 착용도 거의 안한거 같습니다 \n\n눈에 띄는 기스 없고,\n(사실 없긴한데 혹시나 해서 걍 사용감 적음함)\n\n전체적으로 그냥 재질상 생활먼지등이 있습니다 \n재질 및 매트블랙 특성상 좀 잘 묻는듯요\n\n저 외관 하드박스에 살짝 표면 일어남?(사진참조)과 박스 안쪽 쩜얼룩? 있습니다 \n\n택포 가격이니 편히 연락 주셔요 \n발송은 우체국택배로 합니다",
    "condition": "LIGHTLY_USED",
    "sale_status": "SOLD_OUT",
    "is_proshop": false,
    "sales_count": 13,
    "review_rating": 5,
    "review_count": 18,
    "parse_ready": true,
    "reject_reasons": []
  },
  {
    "pid": "390056135",
    "name": "비츠 스튜디오 프로 네이비",
    "price": 180000,
    "num_faved": 0,
    "query": "비츠 스튜디오 프로",
    "description": "작년 8월에 구매하였고 실착 3번정도 해서 상태는 매우 좋습니다 케이스랑 박스 충전 선 까지 다 있습니다 자세한건 번개톡 주시면 빠르게 답변 드리겠습니다!",
    "condition": "LIKE_NEW",
    "sale_status": "SOLD_OUT",
    "is_proshop": false,
    "sales_count": 19,
    "review_rating": 4.9,
    "review_count": 10,
    "parse_ready": true,
    "reject_reasons": []
  },
  {
    "pid": "392121195",
    "name": "비츠 스튜디오 프로 샌드스톤 색상 헤드셋 (노이즈캔슬링)",
    "price": 200000,
    "num_faved": 1,
    "query": "비츠 스튜디오 프로",
    "description": "beats studio pro sandstone\n비츠 스튜디오 프로 샌드스톤 색상 헤드셋입니다. \n노이즈 캔슬링 기능 있습니다. \n박스, 케이블, 파우치까지 풀박스 구성이에요. \n\n진짜 거의 안써서 새상품 같아요!!",
    "condition": "LIKE_NEW",
    "sale_status": "SOLD_OUT",
    "is_proshop": false,
    "sales_count": 113,
    "review_rating": 4.9,
    "review_count": 32,
    "parse_ready": true,
    "reject_reasons": []
  },
  {
    "pid": "390081395",
    "name": "애플 비츠 스튜디오 프로 블랙 헤드폰",
    "price": 160000,
    "num_faved": 1,
    "query": "비츠 스튜디오 프로",
    "description": "애플 비츠 스튜디오 프로 블랙 헤드폰입니다\n몇번 사용하지 않아 상태 좋아요 사진에도 잘 담기지 않는 미세한 찍힘부분 존재합니다 사용하시는데 지장없어요\n\n- 액티브 노이즈 캔슬링(ANC) 기능으로 주변 소음을 효과적으로 차단해 음악에만 집중할 수 있습니다\n- 편안한 착용감으로 장시간 사용에도 불편함이 없습니다",
    "condition": "LIKE_NEW",
    "sale_status": "SOLD_OUT",
    "is_proshop": false,
    "sales_count": 41,
    "review_rating": 4.7,
    "review_count": 33,
    "parse_ready": true,
    "reject_reasons": []
  },
  {
    "pid": "389715959",
    "name": "비츠 스튜디오 프로 판매합니다",
    "price": 130000,
    "num_faved": 5,
    "query": "비츠 스튜디오 프로",
    "description": "비츠 스튜디오 프로 블랙 색상 판매합니다!\n\n오프라인에서 구매 한 정품이며 구매 후 잘 사용하지 않게 되어 판매합니다!\n\n박스 있습니다!",
    "condition": "LIGHTLY_USED",
    "sale_status": "SOLD_OUT",
    "is_proshop": false,
    "sales_count": 14,
    "review_rating": 5,
    "review_count": 7,
    "parse_ready": false,
    "reject_reasons": [
      "price_too_low"
    ]
  },
  {
    "pid": "362390624",
    "name": "애플 정품) 비츠 스튜디오 버즈, 프로 헤드셋입니다.",
    "price": 89000,
    "num_faved": 9,
    "query": "비츠 스튜디오 프로",
    "description": "애플 정품) 비츠 스튜디오 버즈, 프로 헤드셋입니다.\n1. 비츠 스튜디오 버즈 \n  구입 243,000 > 판매 89,000\n2. 비츠 스튜디오 프로 헤드셋 \n  구입 449,000 > 판매 249,000\n아래는 제품 정보 사이트입니다.\nhttps://naver.me/5lfDjp23\n개봉 후 보관하고있어서 저렴하게 내어놓으니 필요하신 분 연락주세요.\n\n편의점 반값 택배는 3,000원, 일반 택배는 5,000원 추금있으며 \n직거래 낮에는 서울 중구 충무로 29 국민은행 앞,\n저녁은 8시 이후에 서울 서대문구 거북골로18나길 43 앞입니다.\n싼 만큼 더 이상의 내고 없으니 꼭 필요한 분만 연락주세요.",
    "condition": "LIKE_NEW",
    "sale_status": "SOLD_OUT",
    "is_proshop": false,
    "sales_count": 231,
    "review_rating": 4.9,
    "review_count": 58,
    "parse_ready": false,
    "reject_reasons": [
      "price_too_low"
    ]
  },
  {
    "pid": "407431405",
    "name": "애플 비츠 솔로 프로 아이보리 Beats Solo Pro 닥터드레 헤드폰",
    "price": 60000,
    "num_faved": 5,
    "query": "비츠 헤드폰 프로",
    "description": "에어팟 구매 해서 안쓰게 될것 같아서 판매합니다",
    "condition": "LIGHTLY_USED",
    "sale_status": "SELLING",
    "is_proshop": false,
    "sales_count": 3,
    "review_rating": 5,
    "review_count": 1,
    "parse_ready": false,
    "reject_reasons": [
      "price_too_low",
      "missing_any_스튜디오_s_프로_스튜디오프로_studio_",
      "reject_wrong_model_solo"
    ]
  },
  {
    "pid": "405811928",
    "name": "스투시x비츠 프로 무선헤드폰 (가격 마지막으루 내려요 ㅠ)",
    "price": 590000,
    "num_faved": 6,
    "query": "비츠 헤드폰 프로",
    "description": "스투시 비츠 스튜디오 프로 무선헤드폰입니다\n작년 구매했구요\n급전필요해서 판매합니다",
    "condition": "LIGHTLY_USED",
    "sale_status": "SELLING",
    "is_proshop": false,
    "sales_count": 12,
    "review_rating": 5,
    "review_count": 7,
    "parse_ready": false,
    "reject_reasons": [
      "price_too_high"
    ]
  },
  {
    "pid": "375484662",
    "name": "비츠 솔로 프로 헤드폰",
    "price": 65000,
    "num_faved": 24,
    "query": "비츠 헤드폰 프로",
    "description": "비츠 솔로 프로 헤드폰 블랙 색상입니다\n케이스 포함이고요, 상태는 사진과 같습니다\n실사용 기간 1년정도 되는것 같습니다\n상태는 B-B+ 정도 되기때문에 \n이 부분 참고해주세요 \n기능적 고장은 없습니다 \n때문에 가격은 싸게 내놓겠습니다",
    "condition": "LIGHTLY_USED",
    "sale_status": "SELLING",
    "is_proshop": false,
    "sales_count": 1,
    "review_rating": 0,
    "review_count": 0,
    "parse_ready": false,
    "reject_reasons": [
      "price_too_low",
      "missing_any_스튜디오_s_프로_스튜디오프로_studio_",
      "reject_broken"
    ]
  },
  {
    "pid": "402456898",
    "name": "애플 비츠 솔로 프로",
    "price": 150000,
    "num_faved": 4,
    "query": "비츠 헤드폰 프로",
    "description": "원가는 30만원이구요 \n오픈형 헤드셋입니다.\n노이즈캔슬링도 되는 힙하면서 편한 제품이에요.\n\n애플제품이라 제품들이랑 호환성 좋습니다!\n\n전용 파우치도 있습니당",
    "condition": "LIGHTLY_USED",
    "sale_status": "SELLING",
    "is_proshop": false,
    "sales_count": 29,
    "review_rating": 5,
    "review_count": 3,
    "parse_ready": false,
    "reject_reasons": [
      "missing_any_스튜디오_s_프로_스튜디오프로_studio_"
    ]
  },
  {
    "pid": "354759231",
    "name": "beats solo pro 팝니다",
    "price": 100000,
    "num_faved": 25,
    "query": "비츠 헤드폰 프로",
    "description": "비츠 솔로 프로 팝니다\n지금은 구하기 힘든 컬러로 \n소장 중에 있는 물건이라 상태 매우 좋습니다",
    "condition": "LIKE_NEW",
    "sale_status": "SELLING",
    "is_proshop": false,
    "sales_count": 82,
    "review_rating": 5,
    "review_count": 37,
    "parse_ready": false,
    "reject_reasons": [
      "price_too_low",
      "missing_any_스튜디오_s_프로_스튜디오프로_studio_",
      "reject_wrong_model_solo"
    ]
  },
  {
    "pid": "310673277",
    "name": "8월까지) 비츠솔로프로 블루(새상품급) 판매합니다!",
    "price": 230000,
    "num_faved": 6,
    "query": "비츠 헤드폰 프로",
    "description": "비츠솔로프로 새상품급 판매합니다!\n완전 새상품급 입니다!\n액세서리, 충전기는 사용하지 않았습니다! 완전 새상품. 헤드폰도 몇번 사용하지 않았으며, 케이스 또한 매우 깨끗합니다!\n\n편하게 연락주세요!\n\n\n❗️택배거래시 파손면책 동의로 간 주합니다.\n\n❗️모든 물품은 중고 거래상 반품과 교환이 불가능 하오니 신중히 구매하시기를 권장드립니다!",
    "condition": "LIKE_NEW",
    "sale_status": "SELLING",
    "is_proshop": false,
    "sales_count": 34,
    "review_rating": 5,
    "review_count": 20,
    "parse_ready": false,
    "reject_reasons": [
      "missing_any_스튜디오_s_프로_스튜디오프로_studio_"
    ]
  },
  {
    "pid": "245492981",
    "name": "비츠 닥터드레 프로 디톡스 24K 골드 한정판 / 몬스터 정품",
    "price": 400000,
    "num_faved": 31,
    "query": "비츠 헤드폰 프로",
    "description": "“현재 단종된 Beats by Dr. Dre Pro Detox 24ct Gold plated Limited Edition 모델입니다. Monster 로고가 들어간 구형 한정판이며, 박스 보유 중입니다. 실사용품이라 생활감은 있으나 외관 존재감이 강하고 수집용으로도 보기 좋은 모델입니다. 작동 확인 후 거래 가능합니다.”\n\n구매시기는 2016년쯤인것같습니다 그당시 환율이쌌음에도 불구하고 이거저거다해서 110만원쯤에구매했습니다 \n리미티드 골드에디션으로 몇개안나온 제품입니다 한국에는 출시조차하지않았습니다 리미티드좋아해서  미국친척한테 부탁해 공수해주어서 샀구요 인증서는 저 안에 워런티라고 써있는 책자같은거입니다 한번도개봉하지않았구요 일단 세월이 있다보니 정말 미세한 스크래치는 좀 있습니다 그래도 가장중요한 스펀지와 이어쪽은 새상품만큼깨끗하게 꾸준히 관리했습니다 많이아껴서요 가슴아프지만 아기기저귀값 벌려고 내놓아요 파우치는워낙 시간이되니 다 삭아서 있긴하지만 안쓰시는걸추천하구요궁금하신게있음  챗부탁드립니다 아기가 있어서 가끔 답이느릴때가있으니 양해부탁드립니다 정말구매원하시는분만 연락주세요 찔러보기 난 깍아주나안깍아주나 간보기사절입니다 좋은하루되세요:)",
    "condition": "LIGHTLY_USED",
    "sale_status": "SELLING",
    "is_proshop": false,
    "sales_count": 6,
    "review_rating": 5,
    "review_count": 2,
    "parse_ready": false,
    "reject_reasons": [
      "missing_any_스튜디오_s_프로_스튜디오프로_studio_"
    ]
  },
  {
    "pid": "397377233",
    "name": "비츠 스튜디오 프로 헤드폰 검정 개봉만한 새상품",
    "price": 180000,
    "num_faved": 0,
    "query": "비츠 헤드폰 프로",
    "description": "오늘 선물 받았는데 개봉만 한 새상품입니다.\n사이즈가 생각보다 작아서 판매합니다.",
    "condition": "NEW",
    "sale_status": "SOLD_OUT",
    "is_proshop": false,
    "sales_count": 15,
    "review_rating": 5,
    "review_count": 8,
    "parse_ready": true,
    "reject_reasons": []
  },
  {
    "pid": "395044662",
    "name": "Apple Beats Solo PRO 비츠 솔로 프로 노이즈캔슬링 헤드폰",
    "price": 73000,
    "num_faved": 5,
    "query": "비츠 헤드폰 프로",
    "description": "비츠 바이 닥터드레 솔로 프로 ANC 헤드셋입니다 ! 깨끗이 관리하여 생활 스크래치 등 제외하면 상태도 좋고 사용이 적어 배터리도 오래갑니다! 노캔이랑 주변소리 듣기 모드 모두 지원되어서 편리하게 사용했어요.\n\n현재까지도 비츠 헤드폰 중 유일한 H2칩 탑재 모델로 에어팟과 동일하게 패스트 페어링, 기기간 자동전환 (아이폰-아이패드-맥북 등) 지원되어서 최신 모델 보다도 편의성 면에서 우월해요! 음질은 비츠 시리즈 최초로 리스너들 사이에서 극찬 받은 제품인 만큼 말할것도 없이 좋습니다. \n\n편하게 연락주세요~~!",
    "condition": "LIKE_NEW",
    "sale_status": "SOLD_OUT",
    "is_proshop": false,
    "sales_count": 382,
    "review_rating": 4.9,
    "review_count": 142,
    "parse_ready": false,
    "reject_reasons": [
      "price_too_low",
      "missing_any_스튜디오_s_프로_스튜디오프로_studio_",
      "reject_wrong_model_solo"
    ]
  },
  {
    "pid": "390511620",
    "name": "애플 비츠 솔로 프로 아이보리 Beats Solo Pro 닥터드레 헤드폰",
    "price": 90000,
    "num_faved": 10,
    "query": "비츠 헤드폰 프로",
    "description": "미개봉 애플 비츠 솔로 프로 아이보리색상입니다. 박스랑 케이스 있고 케이블은 따로 없습니다.\n싸게 급처합니다.\n실착 5회 이하로 외관 아무 문제 없습니다\n노이즈캔슬링 가능한 모델입니다",
    "condition": "LIKE_NEW",
    "sale_status": "SOLD_OUT",
    "is_proshop": false,
    "sales_count": 41,
    "review_rating": 5,
    "review_count": 25,
    "parse_ready": false,
    "reject_reasons": [
      "price_too_low",
      "missing_any_스튜디오_s_프로_스튜디오프로_studio_",
      "reject_wrong_model_solo"
    ]
  },
  {
    "pid": "328889042",
    "name": "비츠 솔로 프로 헤드폰",
    "price": 70000,
    "num_faved": 8,
    "query": "비츠 헤드폰 프로",
    "description": "비츠 솔로 프로 헤드폰 판매합니다.\n연락 주세요.",
    "condition": "LIKE_NEW",
    "sale_status": "SOLD_OUT",
    "is_proshop": false,
    "sales_count": 14,
    "review_rating": 5,
    "review_count": 5,
    "parse_ready": false,
    "reject_reasons": [
      "price_too_low",
      "missing_any_스튜디오_s_프로_스튜디오프로_studio_"
    ]
  },
  {
    "pid": "405620285",
    "name": "닥터드레 Beats Solo Pro 그레이 헤드폰 풀박스",
    "price": 80000,
    "num_faved": 1,
    "query": "비츠 헤드폰 프로",
    "description": "닥터드레 Beats Solo Pro 그레이색상 헤드폰 판매합니다. 풀박스에, 헤드폰 케이스까지 같이 드립니다. \n몇번 사용을 안해서\n상태는 사진 보시는 것과 같이 거의 새것같은 컨디션이에요",
    "condition": "LIKE_NEW",
    "sale_status": "SOLD_OUT",
    "is_proshop": false,
    "sales_count": 382,
    "review_rating": 4.8,
    "review_count": 114,
    "parse_ready": false,
    "reject_reasons": [
      "price_too_low",
      "missing_any_스튜디오_s_프로_스튜디오프로_studio_",
      "reject_wrong_model_solo"
    ]
  },
  {
    "pid": "393449492",
    "name": "비츠솔로 프로",
    "price": 35000,
    "num_faved": 3,
    "query": "비츠 헤드폰 프로",
    "description": "비츠솔로 프로 헤드폰 블랙 색상입니다. \n풀박스 구성이고, 보관 케이스도 같이 드립니다. \n상태는 사진과 동일합니다. \n옆 면에 스크레치 살짝 있지만 신경쓰일 정도 아닙니다\n사용감 약간 있지만 전체적으로 깔끔합니다\n감안해서 저렴하게 올립니다\n\n교환 환불 불가",
    "condition": "LIGHTLY_USED",
    "sale_status": "SOLD_OUT",
    "is_proshop": false,
    "sales_count": 17,
    "review_rating": 5,
    "review_count": 6,
    "parse_ready": false,
    "reject_reasons": [
      "price_too_low",
      "missing_any_스튜디오_s_프로_스튜디오프로_studio_"
    ]
  },
  {
    "pid": "396691945",
    "name": "Beats Solo pro 헤드폰 부품용 팝니다.",
    "price": 25000,
    "num_faved": 3,
    "query": "비츠 헤드폰 프로",
    "description": "단자 연결해도 충전이 안됨. \n\n부품용으로 쓰시거나 수리해서 쓰실분들만 문의주세요.\n\n케이블 포함.",
    "condition": "DAMAGED",
    "sale_status": "SOLD_OUT",
    "is_proshop": false,
    "sales_count": 11,
    "review_rating": 5,
    "review_count": 7,
    "parse_ready": false,
    "reject_reasons": [
      "price_too_low",
      "missing_any_스튜디오_s_프로_스튜디오프로_studio_",
      "reject_wrong_model_solo",
      "reject_parts_only"
    ]
  }
]